driveup/__init__.py
driveup/drive.py
driveup/features/__init__.py
driveup/features/auth.py
driveup/features/service.py
driveup/features/utils.py
driveup-0.9.18.dist-info/licenses/LICENSE
driveup-0.9.18.dist-info/METADATA
driveup-0.9.18.dist-info/WHEEL
driveup-0.9.18.dist-info/top_level.txt
driveup-0.9.18.dist-info/RECORD
