Metadata-Version: 2.4
Name: driveup
Version: 0.9.18
Summary: Python package for uploading files and folders to Google Drive.
Home-page: https://github.com/raul-martin-dev/Driveup
Author: Raúl M.R.
Author-email: raul.martin4bc@gmail.com
License: MIT
Requires-Python: >3.7
License-File: LICENSE
Requires-Dist: google-api-python-client>=2.0.0
Requires-Dist: pandas>=1.0.0
Requires-Dist: google-auth-oauthlib>=0.8.0
Requires-Dist: tqdm
Dynamic: author
Dynamic: author-email
Dynamic: description
Dynamic: description-content-type
Dynamic: home-page
Dynamic: license
Dynamic: license-file
Dynamic: requires-dist
Dynamic: requires-python
Dynamic: summary
